apolloCommon/__init__.py
apolloCommon/commonNetgameApi.py
apolloCommon/extraMongoPool.py
apolloCommon/extraMysqlPool.py
apolloCommon/extraRedisPool.py
apolloCommon/launcherApi.py
apolloCommon/mongoPool.py
apolloCommon/mysqlPool.py
apolloCommon/redisPool.py
apolloCommon/workerPool.py
lobby/__init__.py
lobby/netgameApi.py
lobbyGame/__init__.py
lobbyGame/netgameApi.py
lobbyGame/serverEvent.py
master/__init__.py
master/masterHttp.py
master/netgameApi.py
master/serverEvent.py
master/serverManager.py
mc_netease_sdk_nyrev-3.6.0.64490.post6.dist-info/licenses/LICENSE
mod/__init__.py
mod/client/__init__.py
mod/client/extraClientApi.pyi
mod/client/component/__init__.py
mod/client/component/achievementCompClient.py
mod/client/component/actionCompClient.py
mod/client/component/actorMotionCompClient.py
mod/client/component/actorRenderCompClient.py
mod/client/component/attrCompClient.py
mod/client/component/audioCustomCompClient.py
mod/client/component/auxValueCompClient.py
mod/client/component/biomeCompClient.py
mod/client/component/blockCompClient.py
mod/client/component/blockGeometryCompClient.py
mod/client/component/blockInfoCompClient.pyi
mod/client/component/blockUseEventWhiteListCompClient.py
mod/client/component/brightnessCompClient.py
mod/client/component/cameraCompClient.pyi
mod/client/component/chunkSourceCompClient.py
mod/client/component/collisionBoxCompClient.py
mod/client/component/configCompClient.py
mod/client/component/deviceCompClient.py
mod/client/component/dimensionCompClient.py
mod/client/component/drawingCompClient.py
mod/client/component/drawingShapeCompClient.py
mod/client/component/effectCompClient.pyi
mod/client/component/engineCompFactoryClient.py
mod/client/component/engineEffectBindControlComp.py
mod/client/component/engineTypeCompClient.py
mod/client/component/fogCompClient.py
mod/client/component/frameAniControlComp.py
mod/client/component/frameAniEntityBindComp.py
mod/client/component/frameAniSkeletonBindComp.py
mod/client/component/frameAniTransComp.py
mod/client/component/gameCompClient.pyi
mc_netease_sdk_nyrev-3.6.0.64490.post6.dist-info/METADATA
mc_netease_sdk_nyrev-3.6.0.64490.post6.dist-info/WHEEL
mc_netease_sdk_nyrev-3.6.0.64490.post6.dist-info/top_level.txt
mc_netease_sdk_nyrev-3.6.0.64490.post6.dist-info/RECORD
