Metadata-Version: 2.4
Name: mc-netease-sdk-nyrev
Version: 3.6.0.64490.post6
Summary: Netease ModSDK completion library revised version by Nuoyan
Home-page: https://github.com/charminglee/mc-netease-sdk-nyrev
Author: Nuoyan
Author-email: 1279735247@qq.com
License: MIT
Classifier: Programming Language :: Python :: 2.7
Classifier: Programming Language :: Python :: 3
Classifier: Operating System :: OS Independent
Requires-Python: >=2.7, <4
License-File: LICENSE
Requires-Dist: typing==3.10.0.0; python_version == "2.7"
Requires-Dist: typing-extensions==3.10.0.2; python_version == "2.7"
Requires-Dist: typing==3.7.4.3; python_version >= "3"
Requires-Dist: typing-extensions; python_version >= "3"
Dynamic: author
Dynamic: author-email
Dynamic: classifier
Dynamic: description
Dynamic: description-content-type
Dynamic: home-page
Dynamic: license
Dynamic: license-file
Dynamic: requires-dist
Dynamic: requires-python
Dynamic: summary
